opentelemetry/instrumentation/anthropic/__init__.py
opentelemetry/instrumentation/anthropic/config.py
opentelemetry/instrumentation/anthropic/streaming.py
opentelemetry/instrumentation/anthropic/utils.py
opentelemetry/instrumentation/anthropic/version.py
opentelemetry/instrumentation/chromadb/__init__.py
opentelemetry/instrumentation/chromadb/config.py
opentelemetry/instrumentation/chromadb/utils.py
opentelemetry/instrumentation/chromadb/version.py
opentelemetry/instrumentation/chromadb/wrapper.py
opentelemetry/instrumentation/langchain/__init__.py
opentelemetry/instrumentation/langchain/config.py
opentelemetry/instrumentation/langchain/custom_chat_wrapper.py
opentelemetry/instrumentation/langchain/custom_llm_wrapper.py
opentelemetry/instrumentation/langchain/task_wrapper.py
opentelemetry/instrumentation/langchain/utils.py
opentelemetry/instrumentation/langchain/version.py
opentelemetry/instrumentation/langchain/workflow_wrapper.py
opentelemetry/instrumentation/llamaindex/__init__.py
opentelemetry/instrumentation/llamaindex/base_agent_instrumentor.py
opentelemetry/instrumentation/llamaindex/base_embedding_instrumentor.py
opentelemetry/instrumentation/llamaindex/base_retriever_instrumentor.py
opentelemetry/instrumentation/llamaindex/base_synthesizer_instrumentor.py
opentelemetry/instrumentation/llamaindex/base_tool_instrumentor.py
opentelemetry/instrumentation/llamaindex/config.py
opentelemetry/instrumentation/llamaindex/custom_llm_instrumentor.py
opentelemetry/instrumentation/llamaindex/query_pipeline_instrumentor.py
opentelemetry/instrumentation/llamaindex/retriever_query_engine_instrumentor.py
opentelemetry/instrumentation/llamaindex/utils.py
opentelemetry/instrumentation/llamaindex/version.py
opentelemetry/instrumentation/mistral/__init__.py
opentelemetry/instrumentation/mistral/config.py
opentelemetry/instrumentation/mistral/streaming.py
opentelemetry/instrumentation/mistral/utils.py
opentelemetry/instrumentation/mistral/version.py
infrastack_otel-0.0.3.dist-info/LICENSE
infrastack_otel-0.0.3.dist-info/METADATA
infrastack_otel-0.0.3.dist-info/WHEEL
infrastack_otel-0.0.3.dist-info/top_level.txt
infrastack_otel-0.0.3.dist-info/RECORD
